{
  "name": "@nu-art/file-upload",
  "version": "0.300.0",
  "description": "File Uploader - Express & Typescript based backend framework",
  "keywords": [
    "TacB0sS",
    "infra",
    "nu-art",
    "storm",
    "thunderstorm",
    "typescript"
  ],
  "homepage": "https://github.com/nu-art-js/file-upload",
  "bugs": {
    "url": "https://github.com/nu-art-js/file-upload/issues"
  },
  "repository": {
    "type": "git",
    "url": "git+ssh://git@github.com:nu-art-js/file-upload.git"
  },
  "publishConfig": {
    "directory": "dist",
    "linkDirectory": true
  },
  "license": "Apache-2.0",
  "author": "TacB0sS",
  "main": "index.js",
  "types": "index.d.ts",
  "files": [
    "**/*"
  ],
  "scripts": {
    "build": "tsc"
  },
  "dependencies": {
    "@thunder-storm/firebase": "workspace:*",
    "@thunder-storm/styles": "workspace:*",
    "@nu-art/push-pub-sub": "workspace:*",
    "@thunder-storm/permissions": "workspace:*",
    "@thunder-storm/user-account": "workspace:*",
    "@thunder-storm/core": "workspace:*",
    "@thunder-storm/common": "workspace:*",
    "@google-cloud/common": "^3.0.0",
    "@google-cloud/storage": "^5.14.5",
    "@google-cloud/firestore": "^5.0.0",
    "react": "^18.2.0",
    "jszip": "^3.2.2",
    "express": "^4.18.2",
    "firebase": "^10.7.1",
    "firebase-admin": "11.9.0",
    "firebase-functions": "4.4.1",
    "fs": "0.0.1-security",
    "google-auth-library": "^6.0.6",
    "file-type": "^16.3.0"
  },
  "devDependencies": {
    "@types/react": "^18.0.29",
    "@types/compression": "^1.0.1",
    "@types/express": "^4.17.17"
  }
}
