{
  "packageName": "@nu-art/permissions-shared",
  "packagePath": "/Users/tacb0ss/dev/nu-art/beamz-editable/_thunderstorm/permissions/shared",
  "timestamp": "2025-12-31T10:04:11.622Z",
  "imports": [
    {
      "importingPackage": "@nu-art/permissions-shared",
      "importedSymbol": "ApiDefResolver",
      "sourcePackage": "@nu-art/thunder-db-api-shared",
      "importPath": "@nu-art/thunder-db-api-shared",
      "filePath": "src/main/apis.ts",
      "line": 20,
      "resolved": false,
      "isTypeOnly": false,
      "isNamespace": false,
      "isDefault": false
    },
    {
      "importingPackage": "@nu-art/permissions-shared",
      "importedSymbol": "BodyApi",
      "sourcePackage": "@nu-art/thunder-db-api-shared",
      "importPath": "@nu-art/thunder-db-api-shared",
      "filePath": "src/main/apis.ts",
      "line": 20,
      "resolved": false,
      "isTypeOnly": false,
      "isNamespace": false,
      "isDefault": false
    },
    {
      "importingPackage": "@nu-art/permissions-shared",
      "importedSymbol": "HttpMethod",
      "sourcePackage": "@nu-art/thunder-db-api-shared",
      "importPath": "@nu-art/thunder-db-api-shared",
      "filePath": "src/main/apis.ts",
      "line": 20,
      "resolved": false,
      "isTypeOnly": false,
      "isNamespace": false,
      "isDefault": false
    },
    {
      "importingPackage": "@nu-art/permissions-shared",
      "importedSymbol": "QueryApi",
      "sourcePackage": "@nu-art/thunder-db-api-shared",
      "importPath": "@nu-art/thunder-db-api-shared",
      "filePath": "src/main/apis.ts",
      "line": 20,
      "resolved": false,
      "isTypeOnly": false,
      "isNamespace": false,
      "isDefault": false
    },
    {
      "importingPackage": "@nu-art/permissions-shared",
      "importedSymbol": "Minute",
      "sourcePackage": "@nu-art/ts-common",
      "importPath": "@nu-art/ts-common",
      "filePath": "src/main/apis.ts",
      "line": 21,
      "resolved": false,
      "isTypeOnly": false,
      "isNamespace": false,
      "isDefault": false
    },
    {
      "importingPackage": "@nu-art/permissions-shared",
      "importedSymbol": "PreDB",
      "sourcePackage": "@nu-art/ts-common",
      "importPath": "@nu-art/ts-common",
      "filePath": "src/main/apis.ts",
      "line": 21,
      "resolved": false,
      "isTypeOnly": false,
      "isNamespace": false,
      "isDefault": false
    },
    {
      "importingPackage": "@nu-art/permissions-shared",
      "importedSymbol": "StringMap",
      "sourcePackage": "@nu-art/ts-common",
      "importPath": "@nu-art/ts-common",
      "filePath": "src/main/apis.ts",
      "line": 21,
      "resolved": false,
      "isTypeOnly": false,
      "isNamespace": false,
      "isDefault": false
    },
    {
      "importingPackage": "@nu-art/permissions-shared",
      "importedSymbol": "md5",
      "sourcePackage": "@nu-art/ts-common",
      "importPath": "@nu-art/ts-common",
      "filePath": "src/main/consts.ts",
      "line": 1,
      "resolved": false,
      "isTypeOnly": false,
      "isNamespace": false,
      "isDefault": false
    },
    {
      "importingPackage": "@nu-art/permissions-shared",
      "importedSymbol": "TypedKeyValue",
      "sourcePackage": "@nu-art/ts-common",
      "importPath": "@nu-art/ts-common",
      "filePath": "src/main/types.ts",
      "line": 1,
      "resolved": false,
      "isTypeOnly": false,
      "isNamespace": false,
      "isDefault": false
    },
    {
      "importingPackage": "@nu-art/permissions-shared",
      "importedSymbol": "TypedMap",
      "sourcePackage": "@nu-art/ts-common",
      "importPath": "@nu-art/ts-common",
      "filePath": "src/main/types.ts",
      "line": 1,
      "resolved": false,
      "isTypeOnly": false,
      "isNamespace": false,
      "isDefault": false
    },
    {
      "importingPackage": "@nu-art/permissions-shared",
      "importedSymbol": "UniqueId",
      "sourcePackage": "@nu-art/ts-common",
      "importPath": "@nu-art/ts-common",
      "filePath": "src/main/types.ts",
      "line": 1,
      "resolved": false,
      "isTypeOnly": false,
      "isNamespace": false,
      "isDefault": false
    },
    {
      "importingPackage": "@nu-art/permissions-shared",
      "importedSymbol": "tsValidateRegexp",
      "sourcePackage": "@nu-art/ts-common",
      "importPath": "@nu-art/ts-common",
      "filePath": "src/main/validators.ts",
      "line": 20,
      "resolved": false,
      "isTypeOnly": false,
      "isNamespace": false,
      "isDefault": false
    },
    {
      "importingPackage": "@nu-art/permissions-shared",
      "importedSymbol": "tsValidateUniqueId",
      "sourcePackage": "@nu-art/ts-common",
      "importPath": "@nu-art/ts-common",
      "filePath": "src/main/validators.ts",
      "line": 20,
      "resolved": false,
      "isTypeOnly": false,
      "isNamespace": false,
      "isDefault": false
    },
    {
      "importingPackage": "@nu-art/permissions-shared",
      "importedSymbol": "ApiDefResolver",
      "sourcePackage": "@nu-art/thunder-db-api-shared",
      "importPath": "@nu-art/thunder-db-api-shared",
      "filePath": "src/main/_entity/permission-user/api-def.ts",
      "line": 1,
      "resolved": false,
      "isTypeOnly": false,
      "isNamespace": false,
      "isDefault": false
    },
    {
      "importingPackage": "@nu-art/permissions-shared",
      "importedSymbol": "BodyApi",
      "sourcePackage": "@nu-art/thunder-db-api-shared",
      "importPath": "@nu-art/thunder-db-api-shared",
      "filePath": "src/main/_entity/permission-user/api-def.ts",
      "line": 1,
      "resolved": false,
      "isTypeOnly": false,
      "isNamespace": false,
      "isDefault": false
    },
    {
      "importingPackage": "@nu-art/permissions-shared",
      "importedSymbol": "HttpMethod",
      "sourcePackage": "@nu-art/thunder-db-api-shared",
      "importPath": "@nu-art/thunder-db-api-shared",
      "filePath": "src/main/_entity/permission-user/api-def.ts",
      "line": 1,
      "resolved": false,
      "isTypeOnly": false,
      "isNamespace": false,
      "isDefault": false
    },
    {
      "importingPackage": "@nu-art/permissions-shared",
      "importedSymbol": "DBDef_V3",
      "sourcePackage": "@nu-art/ts-common",
      "importPath": "@nu-art/ts-common",
      "filePath": "src/main/_entity/permission-user/db-def.ts",
      "line": 1,
      "resolved": false,
      "isTypeOnly": false,
      "isNamespace": false,
      "isDefault": false
    },
    {
      "importingPackage": "@nu-art/permissions-shared",
      "importedSymbol": "tsValidateArray",
      "sourcePackage": "@nu-art/ts-common",
      "importPath": "@nu-art/ts-common",
      "filePath": "src/main/_entity/permission-user/db-def.ts",
      "line": 1,
      "resolved": false,
      "isTypeOnly": false,
      "isNamespace": false,
      "isDefault": false
    },
    {
      "importingPackage": "@nu-art/permissions-shared",
      "importedSymbol": "tsValidateString",
      "sourcePackage": "@nu-art/ts-common",
      "importPath": "@nu-art/ts-common",
      "filePath": "src/main/_entity/permission-user/db-def.ts",
      "line": 1,
      "resolved": false,
      "isTypeOnly": false,
      "isNamespace": false,
      "isDefault": false
    },
    {
      "importingPackage": "@nu-art/permissions-shared",
      "importedSymbol": "tsValidateStringAndNumbersWithDashes",
      "sourcePackage": "@nu-art/ts-common",
      "importPath": "@nu-art/ts-common",
      "filePath": "src/main/_entity/permission-user/db-def.ts",
      "line": 1,
      "resolved": false,
      "isTypeOnly": false,
      "isNamespace": false,
      "isDefault": false
    },
    {
      "importingPackage": "@nu-art/permissions-shared",
      "importedSymbol": "AuditableV2",
      "sourcePackage": "@nu-art/ts-common",
      "importPath": "@nu-art/ts-common",
      "filePath": "src/main/_entity/permission-user/types.ts",
      "line": 1,
      "resolved": false,
      "isTypeOnly": false,
      "isNamespace": false,
      "isDefault": false
    },
    {
      "importingPackage": "@nu-art/permissions-shared",
      "importedSymbol": "DB_Object",
      "sourcePackage": "@nu-art/ts-common",
      "importPath": "@nu-art/ts-common",
      "filePath": "src/main/_entity/permission-user/types.ts",
      "line": 1,
      "resolved": false,
      "isTypeOnly": false,
      "isNamespace": false,
      "isDefault": false
    },
    {
      "importingPackage": "@nu-art/permissions-shared",
      "importedSymbol": "DBProto",
      "sourcePackage": "@nu-art/ts-common",
      "importPath": "@nu-art/ts-common",
      "filePath": "src/main/_entity/permission-user/types.ts",
      "line": 1,
      "resolved": false,
      "isTypeOnly": false,
      "isNamespace": false,
      "isDefault": false
    },
    {
      "importingPackage": "@nu-art/permissions-shared",
      "importedSymbol": "Proto_DB_Object",
      "sourcePackage": "@nu-art/ts-common",
      "importPath": "@nu-art/ts-common",
      "filePath": "src/main/_entity/permission-user/types.ts",
      "line": 1,
      "resolved": false,
      "isTypeOnly": false,
      "isNamespace": false,
      "isDefault": false
    },
    {
      "importingPackage": "@nu-art/permissions-shared",
      "importedSymbol": "VersionsDeclaration",
      "sourcePackage": "@nu-art/ts-common",
      "importPath": "@nu-art/ts-common",
      "filePath": "src/main/_entity/permission-user/types.ts",
      "line": 1,
      "resolved": false,
      "isTypeOnly": false,
      "isNamespace": false,
      "isDefault": false
    },
    {
      "importingPackage": "@nu-art/permissions-shared",
      "importedSymbol": "ApiDefResolver",
      "sourcePackage": "@nu-art/thunder-db-api-shared",
      "importPath": "@nu-art/thunder-db-api-shared",
      "filePath": "src/main/_entity/permission-project/api-def.ts",
      "line": 1,
      "resolved": false,
      "isTypeOnly": false,
      "isNamespace": false,
      "isDefault": false
    },
    {
      "importingPackage": "@nu-art/permissions-shared",
      "importedSymbol": "DBDef_V3",
      "sourcePackage": "@nu-art/ts-common",
      "importPath": "@nu-art/ts-common",
      "filePath": "src/main/_entity/permission-project/db-def.ts",
      "line": 1,
      "resolved": false,
      "isTypeOnly": false,
      "isNamespace": false,
      "isDefault": false
    },
    {
      "importingPackage": "@nu-art/permissions-shared",
      "importedSymbol": "tsValidateString",
      "sourcePackage": "@nu-art/ts-common",
      "importPath": "@nu-art/ts-common",
      "filePath": "src/main/_entity/permission-project/db-def.ts",
      "line": 1,
      "resolved": false,
      "isTypeOnly": false,
      "isNamespace": false,
      "isDefault": false
    },
    {
      "importingPackage": "@nu-art/permissions-shared",
      "importedSymbol": "AuditableV2",
      "sourcePackage": "@nu-art/ts-common",
      "importPath": "@nu-art/ts-common",
      "filePath": "src/main/_entity/permission-project/types.ts",
      "line": 1,
      "resolved": false,
      "isTypeOnly": false,
      "isNamespace": false,
      "isDefault": false
    },
    {
      "importingPackage": "@nu-art/permissions-shared",
      "importedSymbol": "DB_Object",
      "sourcePackage": "@nu-art/ts-common",
      "importPath": "@nu-art/ts-common",
      "filePath": "src/main/_entity/permission-project/types.ts",
      "line": 1,
      "resolved": false,
      "isTypeOnly": false,
      "isNamespace": false,
      "isDefault": false
    },
    {
      "importingPackage": "@nu-art/permissions-shared",
      "importedSymbol": "DBProto",
      "sourcePackage": "@nu-art/ts-common",
      "importPath": "@nu-art/ts-common",
      "filePath": "src/main/_entity/permission-project/types.ts",
      "line": 1,
      "resolved": false,
      "isTypeOnly": false,
      "isNamespace": false,
      "isDefault": false
    },
    {
      "importingPackage": "@nu-art/permissions-shared",
      "importedSymbol": "Proto_DB_Object",
      "sourcePackage": "@nu-art/ts-common",
      "importPath": "@nu-art/ts-common",
      "filePath": "src/main/_entity/permission-project/types.ts",
      "line": 1,
      "resolved": false,
      "isTypeOnly": false,
      "isNamespace": false,
      "isDefault": false
    },
    {
      "importingPackage": "@nu-art/permissions-shared",
      "importedSymbol": "VersionsDeclaration",
      "sourcePackage": "@nu-art/ts-common",
      "importPath": "@nu-art/ts-common",
      "filePath": "src/main/_entity/permission-project/types.ts",
      "line": 1,
      "resolved": false,
      "isTypeOnly": false,
      "isNamespace": false,
      "isDefault": false
    },
    {
      "importingPackage": "@nu-art/permissions-shared",
      "importedSymbol": "ApiDefResolver",
      "sourcePackage": "@nu-art/thunder-db-api-shared",
      "importPath": "@nu-art/thunder-db-api-shared",
      "filePath": "src/main/_entity/permission-group/api-def.ts",
      "line": 1,
      "resolved": false,
      "isTypeOnly": false,
      "isNamespace": false,
      "isDefault": false
    },
    {
      "importingPackage": "@nu-art/permissions-shared",
      "importedSymbol": "DBDef_V3",
      "sourcePackage": "@nu-art/ts-common",
      "importPath": "@nu-art/ts-common",
      "filePath": "src/main/_entity/permission-group/db-def.ts",
      "line": 1,
      "resolved": false,
      "isTypeOnly": false,
      "isNamespace": false,
      "isDefault": false
    },
    {
      "importingPackage": "@nu-art/permissions-shared",
      "importedSymbol": "tsValidateArray",
      "sourcePackage": "@nu-art/ts-common",
      "importPath": "@nu-art/ts-common",
      "filePath": "src/main/_entity/permission-group/db-def.ts",
      "line": 1,
      "resolved": false,
      "isTypeOnly": false,
      "isNamespace": false,
      "isDefault": false
    },
    {
      "importingPackage": "@nu-art/permissions-shared",
      "importedSymbol": "tsValidateDynamicObject",
      "sourcePackage": "@nu-art/ts-common",
      "importPath": "@nu-art/ts-common",
      "filePath": "src/main/_entity/permission-group/db-def.ts",
      "line": 1,
      "resolved": false,
      "isTypeOnly": false,
      "isNamespace": false,
      "isDefault": false
    },
    {
      "importingPackage": "@nu-art/permissions-shared",
      "importedSymbol": "tsValidateNumber",
      "sourcePackage": "@nu-art/ts-common",
      "importPath": "@nu-art/ts-common",
      "filePath": "src/main/_entity/permission-group/db-def.ts",
      "line": 1,
      "resolved": false,
      "isTypeOnly": false,
      "isNamespace": false,
      "isDefault": false
    },
    {
      "importingPackage": "@nu-art/permissions-shared",
      "importedSymbol": "tsValidateOptionalId",
      "sourcePackage": "@nu-art/ts-common",
      "importPath": "@nu-art/ts-common",
      "filePath": "src/main/_entity/permission-group/db-def.ts",
      "line": 1,
      "resolved": false,
      "isTypeOnly": false,
      "isNamespace": false,
      "isDefault": false
    },
    {
      "importingPackage": "@nu-art/permissions-shared",
      "importedSymbol": "tsValidateString",
      "sourcePackage": "@nu-art/ts-common",
      "importPath": "@nu-art/ts-common",
      "filePath": "src/main/_entity/permission-group/db-def.ts",
      "line": 1,
      "resolved": false,
      "isTypeOnly": false,
      "isNamespace": false,
      "isDefault": false
    },
    {
      "importingPackage": "@nu-art/permissions-shared",
      "importedSymbol": "tsValidateUniqueId",
      "sourcePackage": "@nu-art/ts-common",
      "importPath": "@nu-art/ts-common",
      "filePath": "src/main/_entity/permission-group/db-def.ts",
      "line": 1,
      "resolved": false,
      "isTypeOnly": false,
      "isNamespace": false,
      "isDefault": false
    },
    {
      "importingPackage": "@nu-art/permissions-shared",
      "importedSymbol": "AuditableV2",
      "sourcePackage": "@nu-art/ts-common",
      "importPath": "@nu-art/ts-common",
      "filePath": "src/main/_entity/permission-group/types.ts",
      "line": 1,
      "resolved": false,
      "isTypeOnly": false,
      "isNamespace": false,
      "isDefault": false
    },
    {
      "importingPackage": "@nu-art/permissions-shared",
      "importedSymbol": "DB_Object",
      "sourcePackage": "@nu-art/ts-common",
      "importPath": "@nu-art/ts-common",
      "filePath": "src/main/_entity/permission-group/types.ts",
      "line": 1,
      "resolved": false,
      "isTypeOnly": false,
      "isNamespace": false,
      "isDefault": false
    },
    {
      "importingPackage": "@nu-art/permissions-shared",
      "importedSymbol": "DBProto",
      "sourcePackage": "@nu-art/ts-common",
      "importPath": "@nu-art/ts-common",
      "filePath": "src/main/_entity/permission-group/types.ts",
      "line": 1,
      "resolved": false,
      "isTypeOnly": false,
      "isNamespace": false,
      "isDefault": false
    },
    {
      "importingPackage": "@nu-art/permissions-shared",
      "importedSymbol": "Proto_DB_Object",
      "sourcePackage": "@nu-art/ts-common",
      "importPath": "@nu-art/ts-common",
      "filePath": "src/main/_entity/permission-group/types.ts",
      "line": 1,
      "resolved": false,
      "isTypeOnly": false,
      "isNamespace": false,
      "isDefault": false
    },
    {
      "importingPackage": "@nu-art/permissions-shared",
      "importedSymbol": "TypedMap",
      "sourcePackage": "@nu-art/ts-common",
      "importPath": "@nu-art/ts-common",
      "filePath": "src/main/_entity/permission-group/types.ts",
      "line": 1,
      "resolved": false,
      "isTypeOnly": false,
      "isNamespace": false,
      "isDefault": false
    },
    {
      "importingPackage": "@nu-art/permissions-shared",
      "importedSymbol": "VersionsDeclaration",
      "sourcePackage": "@nu-art/ts-common",
      "importPath": "@nu-art/ts-common",
      "filePath": "src/main/_entity/permission-group/types.ts",
      "line": 1,
      "resolved": false,
      "isTypeOnly": false,
      "isNamespace": false,
      "isDefault": false
    },
    {
      "importingPackage": "@nu-art/permissions-shared",
      "importedSymbol": "ApiDefResolver",
      "sourcePackage": "@nu-art/thunder-db-api-shared",
      "importPath": "@nu-art/thunder-db-api-shared",
      "filePath": "src/main/_entity/permission-domain/api-def.ts",
      "line": 1,
      "resolved": false,
      "isTypeOnly": false,
      "isNamespace": false,
      "isDefault": false
    },
    {
      "importingPackage": "@nu-art/permissions-shared",
      "importedSymbol": "DBDef_V3",
      "sourcePackage": "@nu-art/ts-common",
      "importPath": "@nu-art/ts-common",
      "filePath": "src/main/_entity/permission-domain/db-def.ts",
      "line": 1,
      "resolved": false,
      "isTypeOnly": false,
      "isNamespace": false,
      "isDefault": false
    },
    {
      "importingPackage": "@nu-art/permissions-shared",
      "importedSymbol": "tsValidateString",
      "sourcePackage": "@nu-art/ts-common",
      "importPath": "@nu-art/ts-common",
      "filePath": "src/main/_entity/permission-domain/db-def.ts",
      "line": 1,
      "resolved": false,
      "isTypeOnly": false,
      "isNamespace": false,
      "isDefault": false
    },
    {
      "importingPackage": "@nu-art/permissions-shared",
      "importedSymbol": "AuditableV2",
      "sourcePackage": "@nu-art/ts-common",
      "importPath": "@nu-art/ts-common",
      "filePath": "src/main/_entity/permission-domain/types.ts",
      "line": 1,
      "resolved": false,
      "isTypeOnly": false,
      "isNamespace": false,
      "isDefault": false
    },
    {
      "importingPackage": "@nu-art/permissions-shared",
      "importedSymbol": "DB_Object",
      "sourcePackage": "@nu-art/ts-common",
      "importPath": "@nu-art/ts-common",
      "filePath": "src/main/_entity/permission-domain/types.ts",
      "line": 1,
      "resolved": false,
      "isTypeOnly": false,
      "isNamespace": false,
      "isDefault": false
    },
    {
      "importingPackage": "@nu-art/permissions-shared",
      "importedSymbol": "DBProto",
      "sourcePackage": "@nu-art/ts-common",
      "importPath": "@nu-art/ts-common",
      "filePath": "src/main/_entity/permission-domain/types.ts",
      "line": 1,
      "resolved": false,
      "isTypeOnly": false,
      "isNamespace": false,
      "isDefault": false
    },
    {
      "importingPackage": "@nu-art/permissions-shared",
      "importedSymbol": "Proto_DB_Object",
      "sourcePackage": "@nu-art/ts-common",
      "importPath": "@nu-art/ts-common",
      "filePath": "src/main/_entity/permission-domain/types.ts",
      "line": 1,
      "resolved": false,
      "isTypeOnly": false,
      "isNamespace": false,
      "isDefault": false
    },
    {
      "importingPackage": "@nu-art/permissions-shared",
      "importedSymbol": "VersionsDeclaration",
      "sourcePackage": "@nu-art/ts-common",
      "importPath": "@nu-art/ts-common",
      "filePath": "src/main/_entity/permission-domain/types.ts",
      "line": 1,
      "resolved": false,
      "isTypeOnly": false,
      "isNamespace": false,
      "isDefault": false
    },
    {
      "importingPackage": "@nu-art/permissions-shared",
      "importedSymbol": "ApiDefResolver",
      "sourcePackage": "@nu-art/thunder-db-api-shared",
      "importPath": "@nu-art/thunder-db-api-shared",
      "filePath": "src/main/_entity/permission-api/api-def.ts",
      "line": 1,
      "resolved": false,
      "isTypeOnly": false,
      "isNamespace": false,
      "isDefault": false
    },
    {
      "importingPackage": "@nu-art/permissions-shared",
      "importedSymbol": "DBDef_V3",
      "sourcePackage": "@nu-art/ts-common",
      "importPath": "@nu-art/ts-common",
      "filePath": "src/main/_entity/permission-api/db-def.ts",
      "line": 1,
      "resolved": false,
      "isTypeOnly": false,
      "isNamespace": false,
      "isDefault": false
    },
    {
      "importingPackage": "@nu-art/permissions-shared",
      "importedSymbol": "tsValidateArray",
      "sourcePackage": "@nu-art/ts-common",
      "importPath": "@nu-art/ts-common",
      "filePath": "src/main/_entity/permission-api/db-def.ts",
      "line": 1,
      "resolved": false,
      "isTypeOnly": false,
      "isNamespace": false,
      "isDefault": false
    },
    {
      "importingPackage": "@nu-art/permissions-shared",
      "importedSymbol": "tsValidateBoolean",
      "sourcePackage": "@nu-art/ts-common",
      "importPath": "@nu-art/ts-common",
      "filePath": "src/main/_entity/permission-api/db-def.ts",
      "line": 1,
      "resolved": false,
      "isTypeOnly": false,
      "isNamespace": false,
      "isDefault": false
    },
    {
      "importingPackage": "@nu-art/permissions-shared",
      "importedSymbol": "tsValidateDynamicObject",
      "sourcePackage": "@nu-art/ts-common",
      "importPath": "@nu-art/ts-common",
      "filePath": "src/main/_entity/permission-api/db-def.ts",
      "line": 1,
      "resolved": false,
      "isTypeOnly": false,
      "isNamespace": false,
      "isDefault": false
    },
    {
      "importingPackage": "@nu-art/permissions-shared",
      "importedSymbol": "tsValidateNumber",
      "sourcePackage": "@nu-art/ts-common",
      "importPath": "@nu-art/ts-common",
      "filePath": "src/main/_entity/permission-api/db-def.ts",
      "line": 1,
      "resolved": false,
      "isTypeOnly": false,
      "isNamespace": false,
      "isDefault": false
    },
    {
      "importingPackage": "@nu-art/permissions-shared",
      "importedSymbol": "tsValidateString",
      "sourcePackage": "@nu-art/ts-common",
      "importPath": "@nu-art/ts-common",
      "filePath": "src/main/_entity/permission-api/db-def.ts",
      "line": 1,
      "resolved": false,
      "isTypeOnly": false,
      "isNamespace": false,
      "isDefault": false
    },
    {
      "importingPackage": "@nu-art/permissions-shared",
      "importedSymbol": "tsValidateUniqueId",
      "sourcePackage": "@nu-art/ts-common",
      "importPath": "@nu-art/ts-common",
      "filePath": "src/main/_entity/permission-api/db-def.ts",
      "line": 1,
      "resolved": false,
      "isTypeOnly": false,
      "isNamespace": false,
      "isDefault": false
    },
    {
      "importingPackage": "@nu-art/permissions-shared",
      "importedSymbol": "AuditableV2",
      "sourcePackage": "@nu-art/ts-common",
      "importPath": "@nu-art/ts-common",
      "filePath": "src/main/_entity/permission-api/types.ts",
      "line": 1,
      "resolved": false,
      "isTypeOnly": false,
      "isNamespace": false,
      "isDefault": false
    },
    {
      "importingPackage": "@nu-art/permissions-shared",
      "importedSymbol": "DB_Object",
      "sourcePackage": "@nu-art/ts-common",
      "importPath": "@nu-art/ts-common",
      "filePath": "src/main/_entity/permission-api/types.ts",
      "line": 1,
      "resolved": false,
      "isTypeOnly": false,
      "isNamespace": false,
      "isDefault": false
    },
    {
      "importingPackage": "@nu-art/permissions-shared",
      "importedSymbol": "DBProto",
      "sourcePackage": "@nu-art/ts-common",
      "importPath": "@nu-art/ts-common",
      "filePath": "src/main/_entity/permission-api/types.ts",
      "line": 1,
      "resolved": false,
      "isTypeOnly": false,
      "isNamespace": false,
      "isDefault": false
    },
    {
      "importingPackage": "@nu-art/permissions-shared",
      "importedSymbol": "Proto_DB_Object",
      "sourcePackage": "@nu-art/ts-common",
      "importPath": "@nu-art/ts-common",
      "filePath": "src/main/_entity/permission-api/types.ts",
      "line": 1,
      "resolved": false,
      "isTypeOnly": false,
      "isNamespace": false,
      "isDefault": false
    },
    {
      "importingPackage": "@nu-art/permissions-shared",
      "importedSymbol": "UniqueId",
      "sourcePackage": "@nu-art/ts-common",
      "importPath": "@nu-art/ts-common",
      "filePath": "src/main/_entity/permission-api/types.ts",
      "line": 1,
      "resolved": false,
      "isTypeOnly": false,
      "isNamespace": false,
      "isDefault": false
    },
    {
      "importingPackage": "@nu-art/permissions-shared",
      "importedSymbol": "VersionsDeclaration",
      "sourcePackage": "@nu-art/ts-common",
      "importPath": "@nu-art/ts-common",
      "filePath": "src/main/_entity/permission-api/types.ts",
      "line": 1,
      "resolved": false,
      "isTypeOnly": false,
      "isNamespace": false,
      "isDefault": false
    },
    {
      "importingPackage": "@nu-art/permissions-shared",
      "importedSymbol": "ApiDefResolver",
      "sourcePackage": "@nu-art/thunder-db-api-shared",
      "importPath": "@nu-art/thunder-db-api-shared",
      "filePath": "src/main/_entity/permission-access-level/api-def.ts",
      "line": 1,
      "resolved": false,
      "isTypeOnly": false,
      "isNamespace": false,
      "isDefault": false
    },
    {
      "importingPackage": "@nu-art/permissions-shared",
      "importedSymbol": "DBDef_V3",
      "sourcePackage": "@nu-art/ts-common",
      "importPath": "@nu-art/ts-common",
      "filePath": "src/main/_entity/permission-access-level/db-def.ts",
      "line": 1,
      "resolved": false,
      "isTypeOnly": false,
      "isNamespace": false,
      "isDefault": false
    },
    {
      "importingPackage": "@nu-art/permissions-shared",
      "importedSymbol": "tsValidateIsInRange",
      "sourcePackage": "@nu-art/ts-common",
      "importPath": "@nu-art/ts-common",
      "filePath": "src/main/_entity/permission-access-level/db-def.ts",
      "line": 1,
      "resolved": false,
      "isTypeOnly": false,
      "isNamespace": false,
      "isDefault": false
    },
    {
      "importingPackage": "@nu-art/permissions-shared",
      "importedSymbol": "tsValidateString",
      "sourcePackage": "@nu-art/ts-common",
      "importPath": "@nu-art/ts-common",
      "filePath": "src/main/_entity/permission-access-level/db-def.ts",
      "line": 1,
      "resolved": false,
      "isTypeOnly": false,
      "isNamespace": false,
      "isDefault": false
    },
    {
      "importingPackage": "@nu-art/permissions-shared",
      "importedSymbol": "tsValidateStringWithDashes",
      "sourcePackage": "@nu-art/ts-common",
      "importPath": "@nu-art/ts-common",
      "filePath": "src/main/_entity/permission-access-level/db-def.ts",
      "line": 1,
      "resolved": false,
      "isTypeOnly": false,
      "isNamespace": false,
      "isDefault": false
    },
    {
      "importingPackage": "@nu-art/permissions-shared",
      "importedSymbol": "tsValidateUniqueId",
      "sourcePackage": "@nu-art/ts-common",
      "importPath": "@nu-art/ts-common",
      "filePath": "src/main/_entity/permission-access-level/db-def.ts",
      "line": 1,
      "resolved": false,
      "isTypeOnly": false,
      "isNamespace": false,
      "isDefault": false
    },
    {
      "importingPackage": "@nu-art/permissions-shared",
      "importedSymbol": "AuditableV2",
      "sourcePackage": "@nu-art/ts-common",
      "importPath": "@nu-art/ts-common",
      "filePath": "src/main/_entity/permission-access-level/types.ts",
      "line": 1,
      "resolved": false,
      "isTypeOnly": false,
      "isNamespace": false,
      "isDefault": false
    },
    {
      "importingPackage": "@nu-art/permissions-shared",
      "importedSymbol": "DB_Object",
      "sourcePackage": "@nu-art/ts-common",
      "importPath": "@nu-art/ts-common",
      "filePath": "src/main/_entity/permission-access-level/types.ts",
      "line": 1,
      "resolved": false,
      "isTypeOnly": false,
      "isNamespace": false,
      "isDefault": false
    },
    {
      "importingPackage": "@nu-art/permissions-shared",
      "importedSymbol": "DBProto",
      "sourcePackage": "@nu-art/ts-common",
      "importPath": "@nu-art/ts-common",
      "filePath": "src/main/_entity/permission-access-level/types.ts",
      "line": 1,
      "resolved": false,
      "isTypeOnly": false,
      "isNamespace": false,
      "isDefault": false
    },
    {
      "importingPackage": "@nu-art/permissions-shared",
      "importedSymbol": "Proto_DB_Object",
      "sourcePackage": "@nu-art/ts-common",
      "importPath": "@nu-art/ts-common",
      "filePath": "src/main/_entity/permission-access-level/types.ts",
      "line": 1,
      "resolved": false,
      "isTypeOnly": false,
      "isNamespace": false,
      "isDefault": false
    },
    {
      "importingPackage": "@nu-art/permissions-shared",
      "importedSymbol": "VersionsDeclaration",
      "sourcePackage": "@nu-art/ts-common",
      "importPath": "@nu-art/ts-common",
      "filePath": "src/main/_entity/permission-access-level/types.ts",
      "line": 1,
      "resolved": false,
      "isTypeOnly": false,
      "isNamespace": false,
      "isDefault": false
    }
  ],
  "dependencies": {
    "required": [
      "@nu-art/thunder-db-api-shared",
      "@nu-art/ts-common"
    ],
    "missing": [],
    "found": [
      "@nu-art/thunder-db-api-shared",
      "@nu-art/ts-common"
    ],
    "unused": []
  },
  "cycles": [],
  "symbolCollisions": []
}